LICENSE
README.md
pyproject.toml
setup.py
sphinxcontrib/kroki/__init__.py
sphinxcontrib/kroki/kroki.py
sphinxcontrib/kroki/transform.py
sphinxcontrib/kroki/util.py
sphinxcontrib_kroki.egg-info/PKG-INFO
sphinxcontrib_kroki.egg-info/SOURCES.txt
sphinxcontrib_kroki.egg-info/dependency_links.txt
sphinxcontrib_kroki.egg-info/requires.txt
sphinxcontrib_kroki.egg-info/top_level.txt