Metadata-Version: 2.1
Name: sphinxcontrib-kroki
Version: 1.2.1
Summary: Kroki integration into sphinx
Home-page: https://github.com/sphinx-contrib/kroki
Author: Martin Hasoň
Author-email: martin.hason@gmail.com
License: UNKNOWN
Platform: UNKNOWN
Classifier: Programming Language :: Python :: 3
Classifier: License :: OSI Approved :: MIT License
Classifier: Operating System :: OS Independent
Requires-Python: >=3.6
Provides-Extra: code
Provides-Extra: test
Provides-Extra: extra
